nxp_dlagent/__init__.py
nxp_dlagent-0.1.0.dist-info/entry_points.txt
nxp_dlagent-0.1.0.dist-info/LICENSE-APACHE
nxp_dlagent-0.1.0.dist-info/LICENSE-MIT
nxp_dlagent-0.1.0.dist-info/WHEEL
nxp_dlagent-0.1.0.dist-info/METADATA
nxp_dlagent-0.1.0.dist-info/RECORD
