Metadata-Version: 2.1
Name: nxp-dlagent
Version: 0.1.0
Summary: Download agent for NXP material
Home-page: https://github.com/nickray/nxp-dlagent
License: UNKNOWN
Author: Nicolas Stalder
Author-email: n@stalder.io
Requires-Python: >=3.6
Classifier: License :: OSI Approved :: MIT License
Classifier: License :: OSI Approved :: Apache Software License
Classifier: Intended Audience :: Developers
Classifier: Intended Audience :: End Users/Desktop
Classifier: Programming Language :: Python :: 3 :: Only
Classifier: Programming Language :: Python :: 3.6
Classifier: Programming Language :: Python :: 3.7
Classifier: Programming Language :: Python :: 3.8
Classifier: Programming Language :: Python :: 3.9
Requires-Dist: selenium
